{
    "name": "SR",
    "color": "green",
    "qualifications": {
        "1011": {
            "dependencies": ["401", "402", "403", "152", "331"]
        },
        "1012": {
            "dependencies": ["401"]
        },
        "1021": {
            "dependencies": ["1011"]
        },
        "1022": {
            "dependencies": ["1011"]
        },
        "1023": {
            "dependencies": ["1011", "1022"]
        },
        "1024": {
            "dependencies": ["1011", "1021"]
        },
        "1025": {
            "dependencies": ["401"]
        },
        "1028": {
            "dependencies": ["1011", "1021", "1022", "421"]
        },
        "1030": {
            "dependencies": ["1028", "830"]
        },
        "1031": {
            "dependencies": ["1028", "831"]
        },
        "1041": {
            "dependencies": ["1028", "1025"]
        },
        "1051": {
            "dependencies": ["1028", "1041"]
        },
        "1081": {
            "dependencies": ["1030", "180.1", "1023"]
        },
        "1082": {
            "dependencies": ["1012", "180.1"]
        },
        "1083": {
            "dependencies": ["1081", "1051"]
        },
        "1091": {
            "dependencies": ["1083", "190.1"]
        }
    }
}